README.md
setup.py
rs/__init__.py
rs/client.py
rs/logger.py
rs/server.py
rs/tfevent.py
rs.egg-info/PKG-INFO
rs.egg-info/SOURCES.txt
rs.egg-info/dependency_links.txt
rs.egg-info/requires.txt
rs.egg-info/top_level.txt